CHANGELOG.txt
LICENSE.txt
MANIFEST.in
README.txt
new_function.py
runlinux.py
setup.cfg
setup.py
alekya/__init__.py
alekya/sample_python_file.py
alekya/sample_tree.py
alekya/sample_tree.txt
alekya.egg-info/PKG-INFO
alekya.egg-info/SOURCES.txt
alekya.egg-info/dependency_links.txt
alekya.egg-info/top_level.txt